{
    "took": 209,
    "timed_out": false,
    "_shards": {
        "total": 5,
        "successful": 5,
        "skipped": 0,
        "failed": 0
    },
    "hits": {
        "total": {
            "value": 10000,
            "relation": "gte"
        },
        "max_score": null,
        "hits": []
    },
    "aggregations": {
        "entities_count_extended_stats": {
            "count": 1851021,
            "min": 1.0,
            "max": 217.0,
            "avg": 39.41817623895137,
            "sum": 7.2963872E7,
            "sum_of_squares": 3.41142864E9,
            "variance": 289.2057272325441,
            "std_deviation": 17.0060497245111,
            "std_deviation_bounds": {
                "upper": 73.43027568797356,
                "lower": 5.406076789929166
            }
        },
        "entities_count_histogram": {
            "buckets": [
                {
                    "key": 1.0,
                    "doc_count": 510
                },
                {
                    "key": 2.0,
                    "doc_count": 972
                },
                {
                    "key": 3.0,
                    "doc_count": 1462
                },
                {
                    "key": 4.0,
                    "doc_count": 2075
                },
                {
                    "key": 5.0,
                    "doc_count": 3106
                },
                {
                    "key": 6.0,
                    "doc_count": 4398
                },
                {
                    "key": 7.0,
                    "doc_count": 5813
                },
                {
                    "key": 8.0,
                    "doc_count": 7437
                },
                {
                    "key": 9.0,
                    "doc_count": 9022
                },
                {
                    "key": 10.0,
                    "doc_count": 10552
                },
                {
                    "key": 11.0,
                    "doc_count": 12104
                },
                {
                    "key": 12.0,
                    "doc_count": 13716
                },
                {
                    "key": 13.0,
                    "doc_count": 15569
                },
                {
                    "key": 14.0,
                    "doc_count": 17383
                },
                {
                    "key": 15.0,
                    "doc_count": 19485
                },
                {
                    "key": 16.0,
                    "doc_count": 21317
                },
                {
                    "key": 17.0,
                    "doc_count": 23264
                },
                {
                    "key": 18.0,
                    "doc_count": 24943
                },
                {
                    "key": 19.0,
                    "doc_count": 27132
                },
                {
                    "key": 20.0,
                    "doc_count": 28770
                },
                {
                    "key": 21.0,
                    "doc_count": 30483
                },
                {
                    "key": 22.0,
                    "doc_count": 31807
                },
                {
                    "key": 23.0,
                    "doc_count": 33568
                },
                {
                    "key": 24.0,
                    "doc_count": 34650
                },
                {
                    "key": 25.0,
                    "doc_count": 36085
                },
                {
                    "key": 26.0,
                    "doc_count": 37516
                },
                {
                    "key": 27.0,
                    "doc_count": 39389
                },
                {
                    "key": 28.0,
                    "doc_count": 39652
                },
                {
                    "key": 29.0,
                    "doc_count": 40600
                },
                {
                    "key": 30.0,
                    "doc_count": 41460
                },
                {
                    "key": 31.0,
                    "doc_count": 42003
                },
                {
                    "key": 32.0,
                    "doc_count": 42109
                },
                {
                    "key": 33.0,
                    "doc_count": 42882
                },
                {
                    "key": 34.0,
                    "doc_count": 42170
                },
                {
                    "key": 35.0,
                    "doc_count": 42040
                },
                {
                    "key": 36.0,
                    "doc_count": 41805
                },
                {
                    "key": 37.0,
                    "doc_count": 41657
                },
                {
                    "key": 38.0,
                    "doc_count": 41003
                },
                {
                    "key": 39.0,
                    "doc_count": 40400
                },
                {
                    "key": 40.0,
                    "doc_count": 39431
                },
                {
                    "key": 41.0,
                    "doc_count": 38892
                },
                {
                    "key": 42.0,
                    "doc_count": 37811
                },
                {
                    "key": 43.0,
                    "doc_count": 37562
                },
                {
                    "key": 44.0,
                    "doc_count": 36149
                },
                {
                    "key": 45.0,
                    "doc_count": 35518
                },
                {
                    "key": 46.0,
                    "doc_count": 34362
                },
                {
                    "key": 47.0,
                    "doc_count": 33452
                },
                {
                    "key": 48.0,
                    "doc_count": 32187
                },
                {
                    "key": 49.0,
                    "doc_count": 31128
                },
                {
                    "key": 50.0,
                    "doc_count": 30141
                },
                {
                    "key": 51.0,
                    "doc_count": 29497
                },
                {
                    "key": 52.0,
                    "doc_count": 28128
                },
                {
                    "key": 53.0,
                    "doc_count": 27274
                },
                {
                    "key": 54.0,
                    "doc_count": 26112
                },
                {
                    "key": 55.0,
                    "doc_count": 25103
                },
                {
                    "key": 56.0,
                    "doc_count": 23525
                },
                {
                    "key": 57.0,
                    "doc_count": 22766
                },
                {
                    "key": 58.0,
                    "doc_count": 21760
                },
                {
                    "key": 59.0,
                    "doc_count": 20736
                },
                {
                    "key": 60.0,
                    "doc_count": 19530
                },
                {
                    "key": 61.0,
                    "doc_count": 18605
                },
                {
                    "key": 62.0,
                    "doc_count": 17583
                },
                {
                    "key": 63.0,
                    "doc_count": 16613
                },
                {
                    "key": 64.0,
                    "doc_count": 15576
                },
                {
                    "key": 65.0,
                    "doc_count": 14772
                },
                {
                    "key": 66.0,
                    "doc_count": 13800
                },
                {
                    "key": 67.0,
                    "doc_count": 13140
                },
                {
                    "key": 68.0,
                    "doc_count": 12123
                },
                {
                    "key": 69.0,
                    "doc_count": 11462
                },
                {
                    "key": 70.0,
                    "doc_count": 10515
                },
                {
                    "key": 71.0,
                    "doc_count": 9635
                },
                {
                    "key": 72.0,
                    "doc_count": 8866
                },
                {
                    "key": 73.0,
                    "doc_count": 8153
                },
                {
                    "key": 74.0,
                    "doc_count": 7465
                },
                {
                    "key": 75.0,
                    "doc_count": 6813
                },
                {
                    "key": 76.0,
                    "doc_count": 6108
                },
                {
                    "key": 77.0,
                    "doc_count": 5390
                },
                {
                    "key": 78.0,
                    "doc_count": 4742
                },
                {
                    "key": 79.0,
                    "doc_count": 4247
                },
                {
                    "key": 80.0,
                    "doc_count": 3787
                },
                {
                    "key": 81.0,
                    "doc_count": 3292
                },
                {
                    "key": 82.0,
                    "doc_count": 2751
                },
                {
                    "key": 83.0,
                    "doc_count": 2504
                },
                {
                    "key": 84.0,
                    "doc_count": 2098
                },
                {
                    "key": 85.0,
                    "doc_count": 1796
                },
                {
                    "key": 86.0,
                    "doc_count": 1438
                },
                {
                    "key": 87.0,
                    "doc_count": 1257
                },
                {
                    "key": 88.0,
                    "doc_count": 1013
                },
                {
                    "key": 89.0,
                    "doc_count": 835
                },
                {
                    "key": 90.0,
                    "doc_count": 685
                },
                {
                    "key": 91.0,
                    "doc_count": 523
                },
                {
                    "key": 92.0,
                    "doc_count": 461
                },
                {
                    "key": 93.0,
                    "doc_count": 349
                },
                {
                    "key": 94.0,
                    "doc_count": 264
                },
                {
                    "key": 95.0,
                    "doc_count": 235
                },
                {
                    "key": 96.0,
                    "doc_count": 165
                },
                {
                    "key": 97.0,
                    "doc_count": 126
                },
                {
                    "key": 98.0,
                    "doc_count": 97
                },
                {
                    "key": 99.0,
                    "doc_count": 71
                },
                {
                    "key": 100.0,
                    "doc_count": 60
                },
                {
                    "key": 101.0,
                    "doc_count": 51
                },
                {
                    "key": 102.0,
                    "doc_count": 32
                },
                {
                    "key": 103.0,
                    "doc_count": 28
                },
                {
                    "key": 104.0,
                    "doc_count": 28
                },
                {
                    "key": 105.0,
                    "doc_count": 8
                },
                {
                    "key": 106.0,
                    "doc_count": 9
                },
                {
                    "key": 107.0,
                    "doc_count": 16
                },
                {
                    "key": 108.0,
                    "doc_count": 8
                },
                {
                    "key": 109.0,
                    "doc_count": 6
                },
                {
                    "key": 110.0,
                    "doc_count": 4
                },
                {
                    "key": 111.0,
                    "doc_count": 5
                },
                {
                    "key": 112.0,
                    "doc_count": 4
                },
                {
                    "key": 113.0,
                    "doc_count": 1
                },
                {
                    "key": 114.0,
                    "doc_count": 4
                },
                {
                    "key": 115.0,
                    "doc_count": 4
                },
                {
                    "key": 116.0,
                    "doc_count": 2
                },
                {
                    "key": 117.0,
                    "doc_count": 3
                },
                {
                    "key": 118.0,
                    "doc_count": 3
                },
                {
                    "key": 119.0,
                    "doc_count": 1
                },
                {
                    "key": 120.0,
                    "doc_count": 1
                },
                {
                    "key": 124.0,
                    "doc_count": 1
                },
                {
                    "key": 125.0,
                    "doc_count": 1
                },
                {
                    "key": 126.0,
                    "doc_count": 1
                },
                {
                    "key": 128.0,
                    "doc_count": 1
                },
                {
                    "key": 129.0,
                    "doc_count": 1
                },
                {
                    "key": 130.0,
                    "doc_count": 1
                },
                {
                    "key": 134.0,
                    "doc_count": 2
                },
                {
                    "key": 137.0,
                    "doc_count": 1
                },
                {
                    "key": 138.0,
                    "doc_count": 1
                },
                {
                    "key": 140.0,
                    "doc_count": 1
                },
                {
                    "key": 141.0,
                    "doc_count": 1
                },
                {
                    "key": 156.0,
                    "doc_count": 1
                },
                {
                    "key": 162.0,
                    "doc_count": 1
                },
                {
                    "key": 217.0,
                    "doc_count": 1
                }
            ]
        }
    }
}